[
    {
        "documento": "Solicitud Crédito",
        "campos": {
            "No.CREADITO": "174185416637",
            "SOLICITUD": "8982592",
            "CEDULA": "1842737500",
            "NOMBRES": "NUBIA LAURA MÉNDEZ",
            "RECOMPRA O DESEMBOLSO": "3.532.422",
            "FIRMA ELLECTRONICA": "NUBIA LAURA MÉNDEZ - 1842737500"
        }
    },
    {
        "documento": "Libranza",
        "campos": {
            "No.CREADITO": "174185416637",
            "NOMBRES": "NUBIA LAURA MÉNDEZ",
            "CREDITO": "6.860.413",
            "PAGADURIA": "INVIAS",
            "CUOTAS": "96",
            "VL.CUOTA": "366.855",
            "FIRMA ELLECTRONICA": "NUBIA LAURA MÉNDEZ - 1842737500",
            "AL PIE DE LA FIRMA": "NUBIA LAURA MÉNDEZ - 1842737500"
        }
    },
    {
        "documento": "Cedula",
        "campos": {
            "CEDULA": "1842737500",
            "NOMBRES": "NUBIA LAURA MÉNDEZ",
            "FECHA NACIMIENTO": "12/04/1988"
        }
    },
    {
        "documento": "Formato conocimiento",
        "campos": {
            "CREDITO": "6.860.413",
            "CUOTAS": "96",
            "FIRMA ELLECTRONICA": "NUBIA LAURA MÉNDEZ - 1842737500",
            "AL PIE DE LA FIRMA": "NUBIA LAURA MÉNDEZ - 1842737500"
        }
    },
    {
        "documento": "Amortización",
        "campos": {
            "SOLICITUD": "8982592",
            "CEDULA": "1842737500",
            "NOMBRES": "NUBIA LAURA MÉNDEZ",
            "CREDITO": "6.860.413",
            "PAGADURIA": "INVIAS",
            "CUOTAS": "96",
            "VL.CUOTA": "366.855",
            "E.A": "21.79%",
            "RECOMPRA O DESEMBOLSO": "3.532.422",
            "FIRMA ELLECTRONICA": "NUBIA LAURA MÉNDEZ - 1842737500"
        }
    },
    {
        "documento": "Seguro de vida",
        "campos": {
            "CEDULA": "1842737500",
            "NOMBRES": "NUBIA LAURA MÉNDEZ",
            "FIRMA ELLECTRONICA": "NUBIA LAURA MÉNDEZ - 1842737500"
        }
    },
    {
        "documento": "Fianza",
        "campos": {
            "CEDULA": "1842737500",
            "NOMBRES": "NUBIA LAURA MÉNDEZ",
            "FIRMA ELLECTRONICA": "NUBIA LAURA MÉNDEZ - 1842737500",
            "AL PIE DE LA FIRMA": "NUBIA LAURA MÉNDEZ - 1842737500"
        }
    },
    {
        "documento": "Datacredito",
        "campos": {
            "NOMBRES": "NUBIA LAURA MÉNDEZ"
        }
    },
    {
        "documento": "Desprendible Nomina",
        "campos": {
            "CEDULA": "1842737500",
            "NOMBRES": "NUBIA LAURA MÉNDEZ",
            "SALARIO": "1.168.378",
            "PAGADURIA": "INVIAS",
            "FECHA DESPRENDIBLE": "02/04/2025"
        }
    },
    {
        "documento": "Soportes recompra o soporte desembolso",
        "campos": {
            "CEDULA": "1842737500",
            "NOMBRES": "NUBIA LAURA MÉNDEZ",
            "RECOMPRA O DESEMBOLSO": "3.532.422"
        }
    }
]