[
    {
        "documento": "Solicitud Crédito",
        "campos": {
            "No.CREADITO": "514204474776",
            "SOLICITUD": "8135241",
            "CEDULA": "1694220748",
            "NOMBRES": "DARY DIANA RENGIFO MENESES",
            "RECOMPRA O DESEMBOLSO": "3.489.681",
            "FIRMA ELLECTRONICA": "DARY DIANA RENGIFO MENESES - 1694220748"
        }
    },
    {
        "documento": "Libranza",
        "campos": {
            "No.CREADITO": "514204474776",
            "NOMBRES": "DARY DIANA RENGIFO MENESES",
            "CREDITO": "13.641.645",
            "PAGADURIA": "COLPENSIONES",
            "CUOTAS": "60",
            "VL.CUOTA": "185.321",
            "FIRMA ELLECTRONICA": "DARY DIANA RENGIFO MENESES - 1694220748",
            "AL PIE DE LA FIRMA": "DARY DIANA RENGIFO MENESES - 1694220748"
        }
    },
    {
        "documento": "Cedula",
        "campos": {
            "CEDULA": "1694220748",
            "NOMBRES": "DARY DIANA RENGIFO MENESES",
            "FECHA NACIMIENTO": "30/04/1973"
        }
    },
    {
        "documento": "Formato conocimiento",
        "campos": {
            "CREDITO": "13.641.645",
            "CUOTAS": "60",
            "FIRMA ELLECTRONICA": "DARY DIANA RENGIFO MENESES - 1694220748",
            "AL PIE DE LA FIRMA": "DARY DIANA RENGIFO MENESES - 1694220748"
        }
    },
    {
        "documento": "Amortización",
        "campos": {
            "SOLICITUD": "8135241",
            "CEDULA": "1694220748",
            "NOMBRES": "DARY DIANA RENGIFO MENESES",
            "CREDITO": "13.641.645",
            "PAGADURIA": "COLPENSIONES",
            "CUOTAS": "60",
            "VL.CUOTA": "185.321",
            "E.A": "22.59%",
            "RECOMPRA O DESEMBOLSO": "3.489.681",
            "FIRMA ELLECTRONICA": "DARY DIANA RENGIFO MENESES - 1694220748"
        }
    },
    {
        "documento": "Seguro de vida",
        "campos": {
            "CEDULA": "1694220748",
            "NOMBRES": "DARY DIANA RENGIFO MENESES",
            "FIRMA ELLECTRONICA": "DARY DIANA RENGIFO MENESES - 1694220748"
        }
    },
    {
        "documento": "Fianza",
        "campos": {
            "CEDULA": "1694220748",
            "NOMBRES": "DARY DIANA RENGIFO MENESES",
            "FIRMA ELLECTRONICA": "DARY DIANA RENGIFO MENESES - 1694220748",
            "AL PIE DE LA FIRMA": "DARY DIANA RENGIFO MENESES - 1694220748"
        }
    },
    {
        "documento": "Datacredito",
        "campos": {
            "NOMBRES": "DARY DIANA RENGIFO MENESES"
        }
    },
    {
        "documento": "Desprendible Nomina",
        "campos": {
            "CEDULA": "1694220748",
            "NOMBRES": "DARY DIANA RENGIFO MENESES",
            "SALARIO": "1.189.647",
            "PAGADURIA": "COLPENSIONES",
            "FECHA DESPRENDIBLE": "21/05/2025"
        }
    },
    {
        "documento": "Soportes recompra o soporte desembolso",
        "campos": {
            "CEDULA": "1694220748",
            "NOMBRES": "DARY DIANA RENGIFO MENESES",
            "RECOMPRA O DESEMBOLSO": "3.489.681"
        }
    }
]