[
    {
        "documento": "Solicitud Crédito",
        "campos": {
            "No.CREADITO": "638709515174",
            "SOLICITUD": "8751419",
            "CEDULA": "1642976502",
            "NOMBRES": "CLAUDIA NELLY BRAVO",
            "RECOMPRA O DESEMBOLSO": "2.709.358",
            "FIRMA ELLECTRONICA": "CLAUDIA NELLY BRAVO - 1642976502"
        }
    },
    {
        "documento": "Libranza",
        "campos": {
            "No.CREADITO": "638709515174",
            "NOMBRES": "CLAUDIA NELLY BRAVO",
            "CREDITO": "14.141.275",
            "PAGADURIA": "INVIAS",
            "CUOTAS": "60",
            "VL.CUOTA": "174.587",
            "FIRMA ELLECTRONICA": "CLAUDIA NELLY BRAVO - 1642976502",
            "AL PIE DE LA FIRMA": "CLAUDIA NELLY BRAVO - 1642976502"
        }
    },
    {
        "documento": "Cedula",
        "campos": {
            "CEDULA": "1642976502",
            "NOMBRES": "CLAUDIA NELLY BRAVO",
            "FECHA NACIMIENTO": "24/01/1981"
        }
    },
    {
        "documento": "Formato conocimiento",
        "campos": {
            "CREDITO": "14.141.275",
            "CUOTAS": "60",
            "FIRMA ELLECTRONICA": "CLAUDIA NELLY BRAVO - 1642976502",
            "AL PIE DE LA FIRMA": "CLAUDIA NELLY BRAVO - 1642976502"
        }
    },
    {
        "documento": "Amortización",
        "campos": {
            "SOLICITUD": "8751419",
            "CEDULA": "1642976502",
            "NOMBRES": "CLAUDIA NELLY BRAVO",
            "CREDITO": "14.141.275",
            "PAGADURIA": "INVIAS",
            "CUOTAS": "60",
            "VL.CUOTA": "174.587",
            "E.A": "22.81%",
            "RECOMPRA O DESEMBOLSO": "2.709.358",
            "FIRMA ELLECTRONICA": "CLAUDIA NELLY BRAVO - 1642976502"
        }
    },
    {
        "documento": "Seguro de vida",
        "campos": {
            "CEDULA": "1642976502",
            "NOMBRES": "CLAUDIA NELLY BRAVO",
            "FIRMA ELLECTRONICA": "CLAUDIA NELLY BRAVO - 1642976502"
        }
    },
    {
        "documento": "Fianza",
        "campos": {
            "CEDULA": "1642976502",
            "NOMBRES": "CLAUDIA NELLY BRAVO",
            "FIRMA ELLECTRONICA": "CLAUDIA NELLY BRAVO - 1642976502",
            "AL PIE DE LA FIRMA": "CLAUDIA NELLY BRAVO - 1642976502"
        }
    },
    {
        "documento": "Datacredito",
        "campos": {
            "NOMBRES": "CLAUDIA NELLY BRAVO"
        }
    },
    {
        "documento": "Desprendible Nomina",
        "campos": {
            "CEDULA": "1642976502",
            "NOMBRES": "CLAUDIA NELLY BRAVO",
            "SALARIO": "3.314.983",
            "PAGADURIA": "INVIAS",
            "FECHA DESPRENDIBLE": "25/02/2025"
        }
    },
    {
        "documento": "Soportes recompra o soporte desembolso",
        "campos": {
            "CEDULA": "1642976502",
            "NOMBRES": "CLAUDIA NELLY BRAVO",
            "RECOMPRA O DESEMBOLSO": "2.709.358"
        }
    }
]