[
    {
        "documento": "Solicitud Crédito",
        "campos": {
            "No.CREADITO": "363744484525",
            "SOLICITUD": "8817156",
            "CEDULA": "1256081221",
            "NOMBRES": "EDGAR TORRES",
            "RECOMPRA O DESEMBOLSO": "1.215.374",
            "FIRMA ELLECTRONICA": "EDGAR TORRES - 1256081221"
        }
    },
    {
        "documento": "Libranza",
        "campos": {
            "No.CREADITO": "363744484525",
            "NOMBRES": "EDGAR TORRES",
            "CREDITO": "14.508.467",
            "PAGADURIA": "SECRETARÍA EDUCACIÓN",
            "CUOTAS": "72",
            "VL.CUOTA": "370.332",
            "FIRMA ELLECTRONICA": "EDGAR TORRES - 1256081221",
            "AL PIE DE LA FIRMA": "EDGAR TORRES - 1256081221"
        }
    },
    {
        "documento": "Cedula",
        "campos": {
            "CEDULA": "1256081221",
            "NOMBRES": "EDGAR TORRES",
            "FECHA NACIMIENTO": "04/09/1955"
        }
    },
    {
        "documento": "Formato conocimiento",
        "campos": {
            "CREDITO": "14.508.467",
            "CUOTAS": "72",
            "FIRMA ELLECTRONICA": "EDGAR TORRES - 1256081221",
            "AL PIE DE LA FIRMA": "EDGAR TORRES - 1256081221"
        }
    },
    {
        "documento": "Amortización",
        "campos": {
            "SOLICITUD": "8817156",
            "CEDULA": "1256081221",
            "NOMBRES": "EDGAR TORRES",
            "CREDITO": "14.508.467",
            "PAGADURIA": "SECRETARÍA EDUCACIÓN",
            "CUOTAS": "72",
            "VL.CUOTA": "370.332",
            "E.A": "21.65%",
            "RECOMPRA O DESEMBOLSO": "1.215.374",
            "FIRMA ELLECTRONICA": "EDGAR TORRES - 1256081221"
        }
    },
    {
        "documento": "Seguro de vida",
        "campos": {
            "CEDULA": "1256081221",
            "NOMBRES": "EDGAR TORRES",
            "FIRMA ELLECTRONICA": "EDGAR TORRES - 1256081221"
        }
    },
    {
        "documento": "Fianza",
        "campos": {
            "CEDULA": "1256081221",
            "NOMBRES": "EDGAR TORRES",
            "FIRMA ELLECTRONICA": "EDGAR TORRES - 1256081221",
            "AL PIE DE LA FIRMA": "EDGAR TORRES - 1256081221"
        }
    },
    {
        "documento": "Datacredito",
        "campos": {
            "NOMBRES": "EDGAR TORRES"
        }
    },
    {
        "documento": "Desprendible Nomina",
        "campos": {
            "CEDULA": "1256081221",
            "NOMBRES": "EDGAR TORRES",
            "SALARIO": "2.187.253",
            "PAGADURIA": "SECRETARÍA EDUCACIÓN",
            "FECHA DESPRENDIBLE": "10/01/2025"
        }
    },
    {
        "documento": "Soportes recompra o soporte desembolso",
        "campos": {
            "CEDULA": "1256081221",
            "NOMBRES": "EDGAR TORRES",
            "RECOMPRA O DESEMBOLSO": "1.215.374"
        }
    }
]