[
    {
        "documento": "Solicitud Crédito",
        "campos": {
            "No.CREADITO": "658270677942",
            "SOLICITUD": "3912280",
            "CEDULA": "1786416937",
            "NOMBRES": "CAMILA YASMÍN MOSQUERA",
            "RECOMPRA O DESEMBOLSO": "2.891.239",
            "FIRMA ELLECTRONICA": "CAMILA YASMÍN MOSQUERA - 1786416937"
        }
    },
    {
        "documento": "Libranza",
        "campos": {
            "No.CREADITO": "658270677942",
            "NOMBRES": "CAMILA YASMÍN MOSQUERA",
            "CREDITO": "19.320.167",
            "PAGADURIA": "FNA",
            "CUOTAS": "96",
            "VL.CUOTA": "171.891",
            "FIRMA ELLECTRONICA": "CAMILA YASMÍN MOSQUERA - 1786416937",
            "AL PIE DE LA FIRMA": "CAMILA YASMÍN MOSQUERA - 1786416937"
        }
    },
    {
        "documento": "Cedula",
        "campos": {
            "CEDULA": "1786416937",
            "NOMBRES": "CAMILA YASMÍN MOSQUERA",
            "FECHA NACIMIENTO": "08/11/1990"
        }
    },
    {
        "documento": "Formato conocimiento",
        "campos": {
            "CREDITO": "19.320.167",
            "CUOTAS": "96",
            "FIRMA ELLECTRONICA": "CAMILA YASMÍN MOSQUERA - 1786416937",
            "AL PIE DE LA FIRMA": "CAMILA YASMÍN MOSQUERA - 1786416937"
        }
    },
    {
        "documento": "Amortización",
        "campos": {
            "SOLICITUD": "3912280",
            "CEDULA": "1786416937",
            "NOMBRES": "CAMILA YASMÍN MOSQUERA",
            "CREDITO": "19.320.167",
            "PAGADURIA": "FNA",
            "CUOTAS": "96",
            "VL.CUOTA": "171.891",
            "E.A": "25.54%",
            "RECOMPRA O DESEMBOLSO": "2.891.239",
            "FIRMA ELLECTRONICA": "CAMILA YASMÍN MOSQUERA - 1786416937"
        }
    },
    {
        "documento": "Seguro de vida",
        "campos": {
            "CEDULA": "1786416937",
            "NOMBRES": "CAMILA YASMÍN MOSQUERA",
            "FIRMA ELLECTRONICA": "CAMILA YASMÍN MOSQUERA - 1786416937"
        }
    },
    {
        "documento": "Fianza",
        "campos": {
            "CEDULA": "1786416937",
            "NOMBRES": "CAMILA YASMÍN MOSQUERA",
            "FIRMA ELLECTRONICA": "CAMILA YASMÍN MOSQUERA - 1786416937",
            "AL PIE DE LA FIRMA": "CAMILA YASMÍN MOSQUERA - 1786416937"
        }
    },
    {
        "documento": "Datacredito",
        "campos": {
            "NOMBRES": "CAMILA YASMÍN MOSQUERA"
        }
    },
    {
        "documento": "Desprendible Nomina",
        "campos": {
            "CEDULA": "1786416937",
            "NOMBRES": "CAMILA YASMÍN MOSQUERA",
            "SALARIO": "3.599.546",
            "PAGADURIA": "FNA",
            "FECHA DESPRENDIBLE": "01/06/2025"
        }
    },
    {
        "documento": "Soportes recompra o soporte desembolso",
        "campos": {
            "CEDULA": "1786416937",
            "NOMBRES": "CAMILA YASMÍN MOSQUERA",
            "RECOMPRA O DESEMBOLSO": "2.891.239"
        }
    }
]