[
    {
        "documento": "Solicitud Crédito",
        "campos": {
            "No.CREADITO": "685349884994",
            "SOLICITUD": "2698350",
            "CEDULA": "1730303722",
            "NOMBRES": "ALEJANDRA RUIZ",
            "RECOMPRA O DESEMBOLSO": "2.218.857",
            "FIRMA ELLECTRONICA": "ALEJANDRA RUIZ - 1730303722"
        }
    },
    {
        "documento": "Libranza",
        "campos": {
            "No.CREADITO": "685349884994",
            "NOMBRES": "ALEJANDRA RUIZ",
            "CREDITO": "6.420.684",
            "PAGADURIA": "COLPENSIONES",
            "CUOTAS": "144",
            "VL.CUOTA": "375.249",
            "FIRMA ELLECTRONICA": "ALEJANDRA RUIZ - 1730303722",
            "AL PIE DE LA FIRMA": "ALEJANDRA RUIZ - 1730303722"
        }
    },
    {
        "documento": "Cedula",
        "campos": {
            "CEDULA": "1730303722",
            "NOMBRES": "ALEJANDRA RUIZ",
            "FECHA NACIMIENTO": "12/06/1962"
        }
    },
    {
        "documento": "Formato conocimiento",
        "campos": {
            "CREDITO": "6.420.684",
            "CUOTAS": "144",
            "FIRMA ELLECTRONICA": "ALEJANDRA RUIZ - 1730303722",
            "AL PIE DE LA FIRMA": "ALEJANDRA RUIZ - 1730303722"
        }
    },
    {
        "documento": "Amortización",
        "campos": {
            "SOLICITUD": "2698350",
            "CEDULA": "1730303722",
            "NOMBRES": "ALEJANDRA RUIZ",
            "CREDITO": "6.420.684",
            "PAGADURIA": "COLPENSIONES",
            "CUOTAS": "144",
            "VL.CUOTA": "375.249",
            "E.A": "18.7%",
            "RECOMPRA O DESEMBOLSO": "2.218.857",
            "FIRMA ELLECTRONICA": "ALEJANDRA RUIZ - 1730303722"
        }
    },
    {
        "documento": "Seguro de vida",
        "campos": {
            "CEDULA": "1730303722",
            "NOMBRES": "ALEJANDRA RUIZ",
            "FIRMA ELLECTRONICA": "ALEJANDRA RUIZ - 1730303722"
        }
    },
    {
        "documento": "Fianza",
        "campos": {
            "CEDULA": "1730303722",
            "NOMBRES": "ALEJANDRA RUIZ",
            "FIRMA ELLECTRONICA": "ALEJANDRA RUIZ - 1730303722",
            "AL PIE DE LA FIRMA": "ALEJANDRA RUIZ - 1730303722"
        }
    },
    {
        "documento": "Datacredito",
        "campos": {
            "NOMBRES": "ALEJANDRA RUIZ"
        }
    },
    {
        "documento": "Desprendible Nomina",
        "campos": {
            "CEDULA": "1730303722",
            "NOMBRES": "ALEJANDRA RUIZ",
            "SALARIO": "2.891.084",
            "PAGADURIA": "COLPENSIONES",
            "FECHA DESPRENDIBLE": "24/01/2025"
        }
    },
    {
        "documento": "Soportes recompra o soporte desembolso",
        "campos": {
            "CEDULA": "1730303722",
            "NOMBRES": "ALEJANDRA RUIZ",
            "RECOMPRA O DESEMBOLSO": "2.218.857"
        }
    }
]