[
    {
        "documento": "Solicitud Crédito",
        "campos": {
            "No.CREADITO": "703046591953",
            "SOLICITUD": "4571592",
            "CEDULA": "1598761405",
            "NOMBRES": "MARÍA LARA",
            "RECOMPRA O DESEMBOLSO": "1.516.057",
            "FIRMA ELLECTRONICA": "MARÍA LARA - 1598761405"
        }
    },
    {
        "documento": "Libranza",
        "campos": {
            "No.CREADITO": "703046591953",
            "NOMBRES": "MARÍA LARA",
            "CREDITO": "5.363.630",
            "PAGADURIA": "COLPENSIONES",
            "CUOTAS": "144",
            "VL.CUOTA": "269.091",
            "FIRMA ELLECTRONICA": "MARÍA LARA - 1598761405",
            "AL PIE DE LA FIRMA": "MARÍA LARA - 1598761405"
        }
    },
    {
        "documento": "Cedula",
        "campos": {
            "CEDULA": "1598761405",
            "NOMBRES": "MARÍA LARA",
            "FECHA NACIMIENTO": "29/08/1961"
        }
    },
    {
        "documento": "Formato conocimiento",
        "campos": {
            "CREDITO": "5.363.630",
            "CUOTAS": "144",
            "FIRMA ELLECTRONICA": "MARÍA LARA - 1598761405",
            "AL PIE DE LA FIRMA": "MARÍA LARA - 1598761405"
        }
    },
    {
        "documento": "Amortización",
        "campos": {
            "SOLICITUD": "4571592",
            "CEDULA": "1598761405",
            "NOMBRES": "MARÍA LARA",
            "CREDITO": "5.363.630",
            "PAGADURIA": "COLPENSIONES",
            "CUOTAS": "144",
            "VL.CUOTA": "269.091",
            "E.A": "18.63%",
            "RECOMPRA O DESEMBOLSO": "1.516.057",
            "FIRMA ELLECTRONICA": "MARÍA LARA - 1598761405"
        }
    },
    {
        "documento": "Seguro de vida",
        "campos": {
            "CEDULA": "1598761405",
            "NOMBRES": "MARÍA LARA",
            "FIRMA ELLECTRONICA": "MARÍA LARA - 1598761405"
        }
    },
    {
        "documento": "Fianza",
        "campos": {
            "CEDULA": "1598761405",
            "NOMBRES": "MARÍA LARA",
            "FIRMA ELLECTRONICA": "MARÍA LARA - 1598761405",
            "AL PIE DE LA FIRMA": "MARÍA LARA - 1598761405"
        }
    },
    {
        "documento": "Datacredito",
        "campos": {
            "NOMBRES": "MARÍA LARA"
        }
    },
    {
        "documento": "Desprendible Nomina",
        "campos": {
            "CEDULA": "1598761405",
            "NOMBRES": "MARÍA LARA",
            "SALARIO": "2.513.742",
            "PAGADURIA": "COLPENSIONES",
            "FECHA DESPRENDIBLE": "23/01/2025"
        }
    },
    {
        "documento": "Soportes recompra o soporte desembolso",
        "campos": {
            "CEDULA": "1598761405",
            "NOMBRES": "MARÍA LARA",
            "RECOMPRA O DESEMBOLSO": "1.516.057"
        }
    }
]