[
    {
        "documento": "Solicitud Crédito",
        "campos": {
            "No.CREADITO": "900981004586",
            "SOLICITUD": "4735123",
            "CEDULA": "1994687015",
            "NOMBRES": "JOSÉ FERNANDO TOVAR FLÓREZ",
            "RECOMPRA O DESEMBOLSO": "1.445.372",
            "FIRMA ELLECTRONICA": "JOSÉ FERNANDO TOVAR FLÓREZ - 1994687015"
        }
    },
    {
        "documento": "Libranza",
        "campos": {
            "No.CREADITO": "900981004586",
            "NOMBRES": "JOSÉ FERNANDO TOVAR FLÓREZ",
            "CREDITO": "10.489.285",
            "PAGADURIA": "FNA",
            "CUOTAS": "72",
            "VL.CUOTA": "285.835",
            "FIRMA ELLECTRONICA": "JOSÉ FERNANDO TOVAR FLÓREZ - 1994687015",
            "AL PIE DE LA FIRMA": "JOSÉ FERNANDO TOVAR FLÓREZ - 1994687015"
        }
    },
    {
        "documento": "Cedula",
        "campos": {
            "CEDULA": "1994687015",
            "NOMBRES": "JOSÉ FERNANDO TOVAR FLÓREZ",
            "FECHA NACIMIENTO": "03/06/1979"
        }
    },
    {
        "documento": "Formato conocimiento",
        "campos": {
            "CREDITO": "10.489.285",
            "CUOTAS": "72",
            "FIRMA ELLECTRONICA": "JOSÉ FERNANDO TOVAR FLÓREZ - 1994687015",
            "AL PIE DE LA FIRMA": "JOSÉ FERNANDO TOVAR FLÓREZ - 1994687015"
        }
    },
    {
        "documento": "Amortización",
        "campos": {
            "SOLICITUD": "4735123",
            "CEDULA": "1994687015",
            "NOMBRES": "JOSÉ FERNANDO TOVAR FLÓREZ",
            "CREDITO": "10.489.285",
            "PAGADURIA": "FNA",
            "CUOTAS": "72",
            "VL.CUOTA": "285.835",
            "E.A": "22.72%",
            "RECOMPRA O DESEMBOLSO": "1.445.372",
            "FIRMA ELLECTRONICA": "JOSÉ FERNANDO TOVAR FLÓREZ - 1994687015"
        }
    },
    {
        "documento": "Seguro de vida",
        "campos": {
            "CEDULA": "1994687015",
            "NOMBRES": "JOSÉ FERNANDO TOVAR FLÓREZ",
            "FIRMA ELLECTRONICA": "JOSÉ FERNANDO TOVAR FLÓREZ - 1994687015"
        }
    },
    {
        "documento": "Fianza",
        "campos": {
            "CEDULA": "1994687015",
            "NOMBRES": "JOSÉ FERNANDO TOVAR FLÓREZ",
            "FIRMA ELLECTRONICA": "JOSÉ FERNANDO TOVAR FLÓREZ - 1994687015",
            "AL PIE DE LA FIRMA": "JOSÉ FERNANDO TOVAR FLÓREZ - 1994687015"
        }
    },
    {
        "documento": "Datacredito",
        "campos": {
            "NOMBRES": "JOSÉ FERNANDO TOVAR FLÓREZ"
        }
    },
    {
        "documento": "Desprendible Nomina",
        "campos": {
            "CEDULA": "1994687015",
            "NOMBRES": "JOSÉ FERNANDO TOVAR FLÓREZ",
            "SALARIO": "4.986.990",
            "PAGADURIA": "FNA",
            "FECHA DESPRENDIBLE": "01/02/2025"
        }
    },
    {
        "documento": "Soportes recompra o soporte desembolso",
        "campos": {
            "CEDULA": "1994687015",
            "NOMBRES": "JOSÉ FERNANDO TOVAR FLÓREZ",
            "RECOMPRA O DESEMBOLSO": "1.445.372"
        }
    }
]