[
    {
        "documento": "Solicitud Crédito",
        "campos": {
            "No.CREADITO": "897671026483",
            "SOLICITUD": "3117655",
            "CEDULA": "1805221044",
            "NOMBRES": "LUIS RUIZ CORREA",
            "RECOMPRA O DESEMBOLSO": "2.428.254",
            "FIRMA ELLECTRONICA": "LUIS RUIZ CORREA - 1805221044"
        }
    },
    {
        "documento": "Libranza",
        "campos": {
            "No.CREADITO": "897671026483",
            "NOMBRES": "LUIS RUIZ CORREA",
            "CREDITO": "11.946.034",
            "PAGADURIA": "COLPENSIONES",
            "CUOTAS": "120",
            "VL.CUOTA": "244.546",
            "FIRMA ELLECTRONICA": "LUIS RUIZ CORREA - 1805221044",
            "AL PIE DE LA FIRMA": "LUIS RUIZ CORREA - 1805221044"
        }
    },
    {
        "documento": "Cedula",
        "campos": {
            "CEDULA": "1805221044",
            "NOMBRES": "LUIS RUIZ CORREA",
            "FECHA NACIMIENTO": "26/12/1973"
        }
    },
    {
        "documento": "Formato conocimiento",
        "campos": {
            "CREDITO": "11.946.034",
            "CUOTAS": "120",
            "FIRMA ELLECTRONICA": "LUIS RUIZ CORREA - 1805221044",
            "AL PIE DE LA FIRMA": "LUIS RUIZ CORREA - 1805221044"
        }
    },
    {
        "documento": "Amortización",
        "campos": {
            "SOLICITUD": "3117655",
            "CEDULA": "1805221044",
            "NOMBRES": "LUIS RUIZ CORREA",
            "CREDITO": "11.946.034",
            "PAGADURIA": "COLPENSIONES",
            "CUOTAS": "120",
            "VL.CUOTA": "244.546",
            "E.A": "20.74%",
            "RECOMPRA O DESEMBOLSO": "2.428.254",
            "FIRMA ELLECTRONICA": "LUIS RUIZ CORREA - 1805221044"
        }
    },
    {
        "documento": "Seguro de vida",
        "campos": {
            "CEDULA": "1805221044",
            "NOMBRES": "LUIS RUIZ CORREA",
            "FIRMA ELLECTRONICA": "LUIS RUIZ CORREA - 1805221044"
        }
    },
    {
        "documento": "Fianza",
        "campos": {
            "CEDULA": "1805221044",
            "NOMBRES": "LUIS RUIZ CORREA",
            "FIRMA ELLECTRONICA": "LUIS RUIZ CORREA - 1805221044",
            "AL PIE DE LA FIRMA": "LUIS RUIZ CORREA - 1805221044"
        }
    },
    {
        "documento": "Datacredito",
        "campos": {
            "NOMBRES": "LUIS RUIZ CORREA"
        }
    },
    {
        "documento": "Desprendible Nomina",
        "campos": {
            "CEDULA": "1805221044",
            "NOMBRES": "LUIS RUIZ CORREA",
            "SALARIO": "4.150.134",
            "PAGADURIA": "COLPENSIONES",
            "FECHA DESPRENDIBLE": "24/02/2025"
        }
    },
    {
        "documento": "Soportes recompra o soporte desembolso",
        "campos": {
            "CEDULA": "1805221044",
            "NOMBRES": "LUIS RUIZ CORREA",
            "RECOMPRA O DESEMBOLSO": "2.428.254"
        }
    }
]