[
    {
        "documento": "Solicitud Crédito",
        "campos": {
            "No.CREADITO": "336724442777",
            "SOLICITUD": "6632929",
            "CEDULA": "1328087864",
            "NOMBRES": "JEAN MERCADO",
            "RECOMPRA O DESEMBOLSO": "4.232.153",
            "FIRMA ELLECTRONICA": "JEAN MERCADO - 1328087864"
        }
    },
    {
        "documento": "Libranza",
        "campos": {
            "No.CREADITO": "336724442777",
            "NOMBRES": "JEAN MERCADO",
            "CREDITO": "16.066.729",
            "PAGADURIA": "INVIAS",
            "CUOTAS": "96",
            "VL.CUOTA": "307.89",
            "FIRMA ELLECTRONICA": "JEAN MERCADO - 1328087864",
            "AL PIE DE LA FIRMA": "JEAN MERCADO - 1328087864"
        }
    },
    {
        "documento": "Cedula",
        "campos": {
            "CEDULA": "1328087864",
            "NOMBRES": "JEAN MERCADO",
            "FECHA NACIMIENTO": "23/04/1975"
        }
    },
    {
        "documento": "Formato conocimiento",
        "campos": {
            "CREDITO": "16.066.729",
            "CUOTAS": "96",
            "FIRMA ELLECTRONICA": "JEAN MERCADO - 1328087864",
            "AL PIE DE LA FIRMA": "JEAN MERCADO - 1328087864"
        }
    },
    {
        "documento": "Amortización",
        "campos": {
            "SOLICITUD": "6632929",
            "CEDULA": "1328087864",
            "NOMBRES": "JEAN MERCADO",
            "CREDITO": "16.066.729",
            "PAGADURIA": "INVIAS",
            "CUOTAS": "96",
            "VL.CUOTA": "307.89",
            "E.A": "21.74%",
            "RECOMPRA O DESEMBOLSO": "4.232.153",
            "FIRMA ELLECTRONICA": "JEAN MERCADO - 1328087864"
        }
    },
    {
        "documento": "Seguro de vida",
        "campos": {
            "CEDULA": "1328087864",
            "NOMBRES": "JEAN MERCADO",
            "FIRMA ELLECTRONICA": "JEAN MERCADO - 1328087864"
        }
    },
    {
        "documento": "Fianza",
        "campos": {
            "CEDULA": "1328087864",
            "NOMBRES": "JEAN MERCADO",
            "FIRMA ELLECTRONICA": "JEAN MERCADO - 1328087864",
            "AL PIE DE LA FIRMA": "JEAN MERCADO - 1328087864"
        }
    },
    {
        "documento": "Datacredito",
        "campos": {
            "NOMBRES": "JEAN MERCADO"
        }
    },
    {
        "documento": "Desprendible Nomina",
        "campos": {
            "CEDULA": "1328087864",
            "NOMBRES": "JEAN MERCADO",
            "SALARIO": "4.392.773",
            "PAGADURIA": "INVIAS",
            "FECHA DESPRENDIBLE": "06/05/2025"
        }
    },
    {
        "documento": "Soportes recompra o soporte desembolso",
        "campos": {
            "CEDULA": "1328087864",
            "NOMBRES": "JEAN MERCADO",
            "RECOMPRA O DESEMBOLSO": "4.232.153"
        }
    }
]