[
    {
        "documento": "Solicitud Crédito",
        "campos": {
            "No.CREADITO": "140223295234",
            "SOLICITUD": "9843415",
            "CEDULA": "1046980397",
            "NOMBRES": "DAVID HERNÁNDEZ RESTREPO",
            "RECOMPRA O DESEMBOLSO": "4.099.067",
            "FIRMA ELLECTRONICA": "DAVID HERNÁNDEZ RESTREPO - 1046980397"
        }
    },
    {
        "documento": "Libranza",
        "campos": {
            "No.CREADITO": "140223295234",
            "NOMBRES": "DAVID HERNÁNDEZ RESTREPO",
            "CREDITO": "9.523.693",
            "PAGADURIA": "FONDO EMPLEADOS BANCOLOMBIA",
            "CUOTAS": "72",
            "VL.CUOTA": "209.069",
            "FIRMA ELLECTRONICA": "DAVID HERNÁNDEZ RESTREPO - 1046980397",
            "AL PIE DE LA FIRMA": "DAVID HERNÁNDEZ RESTREPO - 1046980397"
        }
    },
    {
        "documento": "Cedula",
        "campos": {
            "CEDULA": "1046980397",
            "NOMBRES": "DAVID HERNÁNDEZ RESTREPO",
            "FECHA NACIMIENTO": "13/05/1974"
        }
    },
    {
        "documento": "Formato conocimiento",
        "campos": {
            "CREDITO": "9.523.693",
            "CUOTAS": "72",
            "FIRMA ELLECTRONICA": "DAVID HERNÁNDEZ RESTREPO - 1046980397",
            "AL PIE DE LA FIRMA": "DAVID HERNÁNDEZ RESTREPO - 1046980397"
        }
    },
    {
        "documento": "Amortización",
        "campos": {
            "SOLICITUD": "9843415",
            "CEDULA": "1046980397",
            "NOMBRES": "DAVID HERNÁNDEZ RESTREPO",
            "CREDITO": "9.523.693",
            "PAGADURIA": "FONDO EMPLEADOS BANCOLOMBIA",
            "CUOTAS": "72",
            "VL.CUOTA": "209.069",
            "E.A": "21.09%",
            "RECOMPRA O DESEMBOLSO": "4.099.067",
            "FIRMA ELLECTRONICA": "DAVID HERNÁNDEZ RESTREPO - 1046980397"
        }
    },
    {
        "documento": "Seguro de vida",
        "campos": {
            "CEDULA": "1046980397",
            "NOMBRES": "DAVID HERNÁNDEZ RESTREPO",
            "FIRMA ELLECTRONICA": "DAVID HERNÁNDEZ RESTREPO - 1046980397"
        }
    },
    {
        "documento": "Fianza",
        "campos": {
            "CEDULA": "1046980397",
            "NOMBRES": "DAVID HERNÁNDEZ RESTREPO",
            "FIRMA ELLECTRONICA": "DAVID HERNÁNDEZ RESTREPO - 1046980397",
            "AL PIE DE LA FIRMA": "DAVID HERNÁNDEZ RESTREPO - 1046980397"
        }
    },
    {
        "documento": "Datacredito",
        "campos": {
            "NOMBRES": "DAVID HERNÁNDEZ RESTREPO"
        }
    },
    {
        "documento": "Desprendible Nomina",
        "campos": {
            "CEDULA": "1046980397",
            "NOMBRES": "DAVID HERNÁNDEZ RESTREPO",
            "SALARIO": "4.710.572",
            "PAGADURIA": "FONDO EMPLEADOS BANCOLOMBIA",
            "FECHA DESPRENDIBLE": "26/04/2025"
        }
    },
    {
        "documento": "Soportes recompra o soporte desembolso",
        "campos": {
            "CEDULA": "1046980397",
            "NOMBRES": "DAVID HERNÁNDEZ RESTREPO",
            "RECOMPRA O DESEMBOLSO": "4.099.067"
        }
    }
]