[
    {
        "documento": "Solicitud Crédito",
        "campos": {
            "No.CREADITO": "243145742064",
            "SOLICITUD": "8716027",
            "CEDULA": "1835751132",
            "NOMBRES": "LUZ DIANA VARGAS",
            "RECOMPRA O DESEMBOLSO": "1.793.794",
            "FIRMA ELLECTRONICA": "LUZ DIANA VARGAS - 1835751132"
        }
    },
    {
        "documento": "Libranza",
        "campos": {
            "No.CREADITO": "243145742064",
            "NOMBRES": "LUZ DIANA VARGAS",
            "CREDITO": "18.566.152",
            "PAGADURIA": "COLPENSIONES",
            "CUOTAS": "96",
            "VL.CUOTA": "173.309",
            "FIRMA ELLECTRONICA": "LUZ DIANA VARGAS - 1835751132",
            "AL PIE DE LA FIRMA": "LUZ DIANA VARGAS - 1835751132"
        }
    },
    {
        "documento": "Cedula",
        "campos": {
            "CEDULA": "1835751132",
            "NOMBRES": "LUZ DIANA VARGAS",
            "FECHA NACIMIENTO": "05/02/1995"
        }
    },
    {
        "documento": "Formato conocimiento",
        "campos": {
            "CREDITO": "18.566.152",
            "CUOTAS": "96",
            "FIRMA ELLECTRONICA": "LUZ DIANA VARGAS - 1835751132",
            "AL PIE DE LA FIRMA": "LUZ DIANA VARGAS - 1835751132"
        }
    },
    {
        "documento": "Amortización",
        "campos": {
            "SOLICITUD": "8716027",
            "CEDULA": "1835751132",
            "NOMBRES": "LUZ DIANA VARGAS",
            "CREDITO": "18.566.152",
            "PAGADURIA": "COLPENSIONES",
            "CUOTAS": "96",
            "VL.CUOTA": "173.309",
            "E.A": "19.9%",
            "RECOMPRA O DESEMBOLSO": "1.793.794",
            "FIRMA ELLECTRONICA": "LUZ DIANA VARGAS - 1835751132"
        }
    },
    {
        "documento": "Seguro de vida",
        "campos": {
            "CEDULA": "1835751132",
            "NOMBRES": "LUZ DIANA VARGAS",
            "FIRMA ELLECTRONICA": "LUZ DIANA VARGAS - 1835751132"
        }
    },
    {
        "documento": "Fianza",
        "campos": {
            "CEDULA": "1835751132",
            "NOMBRES": "LUZ DIANA VARGAS",
            "FIRMA ELLECTRONICA": "LUZ DIANA VARGAS - 1835751132",
            "AL PIE DE LA FIRMA": "LUZ DIANA VARGAS - 1835751132"
        }
    },
    {
        "documento": "Datacredito",
        "campos": {
            "NOMBRES": "LUZ DIANA VARGAS"
        }
    },
    {
        "documento": "Desprendible Nomina",
        "campos": {
            "CEDULA": "1835751132",
            "NOMBRES": "LUZ DIANA VARGAS",
            "SALARIO": "1.597.023",
            "PAGADURIA": "COLPENSIONES",
            "FECHA DESPRENDIBLE": "08/06/2025"
        }
    },
    {
        "documento": "Soportes recompra o soporte desembolso",
        "campos": {
            "CEDULA": "1835751132",
            "NOMBRES": "LUZ DIANA VARGAS",
            "RECOMPRA O DESEMBOLSO": "1.793.794"
        }
    }
]