[
    {
        "documento": "Solicitud Crédito",
        "campos": {
            "No.CREADITO": "565552485466",
            "SOLICITUD": "9537306",
            "CEDULA": "1215587161",
            "NOMBRES": "DANIEL JULIÁN ÁLVAREZ CALDERÓN",
            "RECOMPRA O DESEMBOLSO": "1.207.815",
            "FIRMA ELLECTRONICA": "DANIEL JULIÁN ÁLVAREZ CALDERÓN - 1215587161"
        }
    },
    {
        "documento": "Libranza",
        "campos": {
            "No.CREADITO": "565552485466",
            "NOMBRES": "DANIEL JULIÁN ÁLVAREZ CALDERÓN",
            "CREDITO": "17.757.697",
            "PAGADURIA": "COLPENSIONES",
            "CUOTAS": "120",
            "VL.CUOTA": "320.094",
            "FIRMA ELLECTRONICA": "DANIEL JULIÁN ÁLVAREZ CALDERÓN - 1215587161",
            "AL PIE DE LA FIRMA": "DANIEL JULIÁN ÁLVAREZ CALDERÓN - 1215587161"
        }
    },
    {
        "documento": "Cedula",
        "campos": {
            "CEDULA": "1215587161",
            "NOMBRES": "DANIEL JULIÁN ÁLVAREZ CALDERÓN",
            "FECHA NACIMIENTO": "04/12/1970"
        }
    },
    {
        "documento": "Formato conocimiento",
        "campos": {
            "CREDITO": "17.757.697",
            "CUOTAS": "120",
            "FIRMA ELLECTRONICA": "DANIEL JULIÁN ÁLVAREZ CALDERÓN - 1215587161",
            "AL PIE DE LA FIRMA": "DANIEL JULIÁN ÁLVAREZ CALDERÓN - 1215587161"
        }
    },
    {
        "documento": "Amortización",
        "campos": {
            "SOLICITUD": "9537306",
            "CEDULA": "1215587161",
            "NOMBRES": "DANIEL JULIÁN ÁLVAREZ CALDERÓN",
            "CREDITO": "17.757.697",
            "PAGADURIA": "COLPENSIONES",
            "CUOTAS": "120",
            "VL.CUOTA": "320.094",
            "E.A": "27.7%",
            "RECOMPRA O DESEMBOLSO": "1.207.815",
            "FIRMA ELLECTRONICA": "DANIEL JULIÁN ÁLVAREZ CALDERÓN - 1215587161"
        }
    },
    {
        "documento": "Seguro de vida",
        "campos": {
            "CEDULA": "1215587161",
            "NOMBRES": "DANIEL JULIÁN ÁLVAREZ CALDERÓN",
            "FIRMA ELLECTRONICA": "DANIEL JULIÁN ÁLVAREZ CALDERÓN - 1215587161"
        }
    },
    {
        "documento": "Fianza",
        "campos": {
            "CEDULA": "1215587161",
            "NOMBRES": "DANIEL JULIÁN ÁLVAREZ CALDERÓN",
            "FIRMA ELLECTRONICA": "DANIEL JULIÁN ÁLVAREZ CALDERÓN - 1215587161",
            "AL PIE DE LA FIRMA": "DANIEL JULIÁN ÁLVAREZ CALDERÓN - 1215587161"
        }
    },
    {
        "documento": "Datacredito",
        "campos": {
            "NOMBRES": "DANIEL JULIÁN ÁLVAREZ CALDERÓN"
        }
    },
    {
        "documento": "Desprendible Nomina",
        "campos": {
            "CEDULA": "1215587161",
            "NOMBRES": "DANIEL JULIÁN ÁLVAREZ CALDERÓN",
            "SALARIO": "1.669.758",
            "PAGADURIA": "COLPENSIONES",
            "FECHA DESPRENDIBLE": "09/05/2025"
        }
    },
    {
        "documento": "Soportes recompra o soporte desembolso",
        "campos": {
            "CEDULA": "1215587161",
            "NOMBRES": "DANIEL JULIÁN ÁLVAREZ CALDERÓN",
            "RECOMPRA O DESEMBOLSO": "1.207.815"
        }
    }
]