[
    {
        "documento": "Solicitud Crédito",
        "campos": {
            "No.CREADITO": "319064864750",
            "SOLICITUD": "1675443",
            "CEDULA": "1077162117",
            "NOMBRES": "JEFFERSON CARLOS MARTÍNEZ DÍAZ",
            "RECOMPRA O DESEMBOLSO": "3.866.396",
            "FIRMA ELLECTRONICA": "JEFFERSON CARLOS MARTÍNEZ DÍAZ - 1077162117"
        }
    },
    {
        "documento": "Libranza",
        "campos": {
            "No.CREADITO": "319064864750",
            "NOMBRES": "JEFFERSON CARLOS MARTÍNEZ DÍAZ",
            "CREDITO": "16.952.775",
            "PAGADURIA": "COLPENSIONES",
            "CUOTAS": "72",
            "VL.CUOTA": "377.757",
            "FIRMA ELLECTRONICA": "JEFFERSON CARLOS MARTÍNEZ DÍAZ - 1077162117",
            "AL PIE DE LA FIRMA": "JEFFERSON CARLOS MARTÍNEZ DÍAZ - 1077162117"
        }
    },
    {
        "documento": "Cedula",
        "campos": {
            "CEDULA": "1077162117",
            "NOMBRES": "JEFFERSON CARLOS MARTÍNEZ DÍAZ",
            "FECHA NACIMIENTO": "30/09/1954"
        }
    },
    {
        "documento": "Formato conocimiento",
        "campos": {
            "CREDITO": "16.952.775",
            "CUOTAS": "72",
            "FIRMA ELLECTRONICA": "JEFFERSON CARLOS MARTÍNEZ DÍAZ - 1077162117",
            "AL PIE DE LA FIRMA": "JEFFERSON CARLOS MARTÍNEZ DÍAZ - 1077162117"
        }
    },
    {
        "documento": "Amortización",
        "campos": {
            "SOLICITUD": "1675443",
            "CEDULA": "1077162117",
            "NOMBRES": "JEFFERSON CARLOS MARTÍNEZ DÍAZ",
            "CREDITO": "16.952.775",
            "PAGADURIA": "COLPENSIONES",
            "CUOTAS": "72",
            "VL.CUOTA": "377.757",
            "E.A": "27.17%",
            "RECOMPRA O DESEMBOLSO": "3.866.396",
            "FIRMA ELLECTRONICA": "JEFFERSON CARLOS MARTÍNEZ DÍAZ - 1077162117"
        }
    },
    {
        "documento": "Seguro de vida",
        "campos": {
            "CEDULA": "1077162117",
            "NOMBRES": "JEFFERSON CARLOS MARTÍNEZ DÍAZ",
            "FIRMA ELLECTRONICA": "JEFFERSON CARLOS MARTÍNEZ DÍAZ - 1077162117"
        }
    },
    {
        "documento": "Fianza",
        "campos": {
            "CEDULA": "1077162117",
            "NOMBRES": "JEFFERSON CARLOS MARTÍNEZ DÍAZ",
            "FIRMA ELLECTRONICA": "JEFFERSON CARLOS MARTÍNEZ DÍAZ - 1077162117",
            "AL PIE DE LA FIRMA": "JEFFERSON CARLOS MARTÍNEZ DÍAZ - 1077162117"
        }
    },
    {
        "documento": "Datacredito",
        "campos": {
            "NOMBRES": "JEFFERSON CARLOS MARTÍNEZ DÍAZ"
        }
    },
    {
        "documento": "Desprendible Nomina",
        "campos": {
            "CEDULA": "1077162117",
            "NOMBRES": "JEFFERSON CARLOS MARTÍNEZ DÍAZ",
            "SALARIO": "2.938.968",
            "PAGADURIA": "COLPENSIONES",
            "FECHA DESPRENDIBLE": "23/04/2025"
        }
    },
    {
        "documento": "Soportes recompra o soporte desembolso",
        "campos": {
            "CEDULA": "1077162117",
            "NOMBRES": "JEFFERSON CARLOS MARTÍNEZ DÍAZ",
            "RECOMPRA O DESEMBOLSO": "3.866.396"
        }
    }
]